{"diffoscope-json-version": 1, "source1": "/mnt/original-11.0.1-open/TryWithResource.class", "source2": "/mnt/proposed-8.0.442-zulu/TryWithResource.class", "unified_diff": null, "details": [{"source1": "javap -verbose -constants -s -l -private {}", "source2": "javap -verbose -constants -s -l -private {}", "unified_diff": "@@ -1,60 +1,62 @@\n-  SHA-256 checksum 3adee6d4c92fe2cc6cd9881def819c2c510a6e7ae76fc2a1a350264ced4cf1b1\n+  SHA-256 checksum 3bd84ffdd4166094c94ff8b9c7969db8a1c6e6bc28f0364a387f4586c6c4ef04\n   Compiled from \"TryWithResource.java\"\n public class TryWithResource\n   minor version: 0\n   major version: 52\n   flags: (0x0021) ACC_PUBLIC, ACC_SUPER\n   this_class: #10                         // TryWithResource\n   super_class: #11                        // java/lang/Object\n   interfaces: 0, fields: 0, methods: 2, attributes: 1\n Constant pool:\n-   #1 = Methodref          #11.#22        // java/lang/Object.\"<init>\":()V\n-   #2 = Class              #23            // java/io/PrintWriter\n-   #3 = Fieldref           #24.#25        // java/lang/System.out:Ljava/io/PrintStream;\n-   #4 = Methodref          #2.#26         // java/io/PrintWriter.\"<init>\":(Ljava/io/OutputStream;)V\n-   #5 = String             #27            // Hello, World!\n-   #6 = Methodref          #2.#28         // java/io/PrintWriter.println:(Ljava/lang/String;)V\n-   #7 = Methodref          #2.#29         // java/io/PrintWriter.close:()V\n-   #8 = Class              #30            // java/lang/Throwable\n-   #9 = Methodref          #8.#31         // java/lang/Throwable.addSuppressed:(Ljava/lang/Throwable;)V\n-  #10 = Class              #32            // TryWithResource\n-  #11 = Class              #33            // java/lang/Object\n+   #1 = Methodref          #11.#24        // java/lang/Object.\"<init>\":()V\n+   #2 = Class              #25            // java/io/PrintWriter\n+   #3 = Fieldref           #26.#27        // java/lang/System.out:Ljava/io/PrintStream;\n+   #4 = Methodref          #2.#28         // java/io/PrintWriter.\"<init>\":(Ljava/io/OutputStream;)V\n+   #5 = String             #29            // Hello, World!\n+   #6 = Methodref          #2.#30         // java/io/PrintWriter.println:(Ljava/lang/String;)V\n+   #7 = Methodref          #2.#31         // java/io/PrintWriter.close:()V\n+   #8 = Class              #32            // java/lang/Throwable\n+   #9 = Methodref          #8.#33         // java/lang/Throwable.addSuppressed:(Ljava/lang/Throwable;)V\n+  #10 = Class              #34            // TryWithResource\n+  #11 = Class              #35            // java/lang/Object\n   #12 = Utf8               <init>\n   #13 = Utf8               ()V\n   #14 = Utf8               Code\n   #15 = Utf8               LineNumberTable\n   #16 = Utf8               main\n   #17 = Utf8               ([Ljava/lang/String;)V\n   #18 = Utf8               StackMapTable\n-  #19 = Class              #34            // \"[Ljava/lang/String;\"\n-  #20 = Utf8               SourceFile\n-  #21 = Utf8               TryWithResource.java\n-  #22 = NameAndType        #12:#13        // \"<init>\":()V\n-  #23 = Utf8               java/io/PrintWriter\n-  #24 = Class              #35            // java/lang/System\n-  #25 = NameAndType        #36:#37        // out:Ljava/io/PrintStream;\n-  #26 = NameAndType        #12:#38        // \"<init>\":(Ljava/io/OutputStream;)V\n-  #27 = Utf8               Hello, World!\n-  #28 = NameAndType        #39:#40        // println:(Ljava/lang/String;)V\n-  #29 = NameAndType        #41:#13        // close:()V\n-  #30 = Utf8               java/lang/Throwable\n-  #31 = NameAndType        #42:#43        // addSuppressed:(Ljava/lang/Throwable;)V\n-  #32 = Utf8               TryWithResource\n-  #33 = Utf8               java/lang/Object\n-  #34 = Utf8               [Ljava/lang/String;\n-  #35 = Utf8               java/lang/System\n-  #36 = Utf8               out\n-  #37 = Utf8               Ljava/io/PrintStream;\n-  #38 = Utf8               (Ljava/io/OutputStream;)V\n-  #39 = Utf8               println\n-  #40 = Utf8               (Ljava/lang/String;)V\n-  #41 = Utf8               close\n-  #42 = Utf8               addSuppressed\n-  #43 = Utf8               (Ljava/lang/Throwable;)V\n+  #19 = Class              #36            // \"[Ljava/lang/String;\"\n+  #20 = Class              #25            // java/io/PrintWriter\n+  #21 = Class              #32            // java/lang/Throwable\n+  #22 = Utf8               SourceFile\n+  #23 = Utf8               TryWithResource.java\n+  #24 = NameAndType        #12:#13        // \"<init>\":()V\n+  #25 = Utf8               java/io/PrintWriter\n+  #26 = Class              #37            // java/lang/System\n+  #27 = NameAndType        #38:#39        // out:Ljava/io/PrintStream;\n+  #28 = NameAndType        #12:#40        // \"<init>\":(Ljava/io/OutputStream;)V\n+  #29 = Utf8               Hello, World!\n+  #30 = NameAndType        #41:#42        // println:(Ljava/lang/String;)V\n+  #31 = NameAndType        #43:#13        // close:()V\n+  #32 = Utf8               java/lang/Throwable\n+  #33 = NameAndType        #44:#45        // addSuppressed:(Ljava/lang/Throwable;)V\n+  #34 = Utf8               TryWithResource\n+  #35 = Utf8               java/lang/Object\n+  #36 = Utf8               [Ljava/lang/String;\n+  #37 = Utf8               java/lang/System\n+  #38 = Utf8               out\n+  #39 = Utf8               Ljava/io/PrintStream;\n+  #40 = Utf8               (Ljava/io/OutputStream;)V\n+  #41 = Utf8               println\n+  #42 = Utf8               (Ljava/lang/String;)V\n+  #43 = Utf8               close\n+  #44 = Utf8               addSuppressed\n+  #45 = Utf8               (Ljava/lang/Throwable;)V\n {\n   public TryWithResource();\n     descriptor: ()V\n     flags: (0x0001) ACC_PUBLIC\n     Code:\n       stack=1, locals=1, args_size=1\n          0: aload_0\n@@ -63,54 +65,92 @@\n       LineNumberTable:\n         line 4: 0\n \n   public static void main(java.lang.String[]);\n     descriptor: ([Ljava/lang/String;)V\n     flags: (0x0009) ACC_PUBLIC, ACC_STATIC\n     Code:\n-      stack=3, locals=4, args_size=1\n+      stack=3, locals=6, args_size=1\n          0: new           #2                  // class java/io/PrintWriter\n          3: dup\n          4: getstatic     #3                  // Field java/lang/System.out:Ljava/io/PrintStream;\n          7: invokespecial #4                  // Method java/io/PrintWriter.\"<init>\":(Ljava/io/OutputStream;)V\n         10: astore_1\n-        11: aload_1\n-        12: ldc           #5                  // String Hello, World!\n-        14: invokevirtual #6                  // Method java/io/PrintWriter.println:(Ljava/lang/String;)V\n-        17: aload_1\n-        18: invokevirtual #7                  // Method java/io/PrintWriter.close:()V\n-        21: goto          40\n-        24: astore_2\n-        25: aload_1\n-        26: invokevirtual #7                  // Method java/io/PrintWriter.close:()V\n-        29: goto          38\n-        32: astore_3\n-        33: aload_2\n-        34: aload_3\n-        35: invokevirtual #9                  // Method java/lang/Throwable.addSuppressed:(Ljava/lang/Throwable;)V\n-        38: aload_2\n-        39: athrow\n-        40: return\n+        11: aconst_null\n+        12: astore_2\n+        13: aload_1\n+        14: ldc           #5                  // String Hello, World!\n+        16: invokevirtual #6                  // Method java/io/PrintWriter.println:(Ljava/lang/String;)V\n+        19: aload_1\n+        20: ifnull        90\n+        23: aload_2\n+        24: ifnull        43\n+        27: aload_1\n+        28: invokevirtual #7                  // Method java/io/PrintWriter.close:()V\n+        31: goto          90\n+        34: astore_3\n+        35: aload_2\n+        36: aload_3\n+        37: invokevirtual #9                  // Method java/lang/Throwable.addSuppressed:(Ljava/lang/Throwable;)V\n+        40: goto          90\n+        43: aload_1\n+        44: invokevirtual #7                  // Method java/io/PrintWriter.close:()V\n+        47: goto          90\n+        50: astore_3\n+        51: aload_3\n+        52: astore_2\n+        53: aload_3\n+        54: athrow\n+        55: astore        4\n+        57: aload_1\n+        58: ifnull        87\n+        61: aload_2\n+        62: ifnull        83\n+        65: aload_1\n+        66: invokevirtual #7                  // Method java/io/PrintWriter.close:()V\n+        69: goto          87\n+        72: astore        5\n+        74: aload_2\n+        75: aload         5\n+        77: invokevirtual #9                  // Method java/lang/Throwable.addSuppressed:(Ljava/lang/Throwable;)V\n+        80: goto          87\n+        83: aload_1\n+        84: invokevirtual #7                  // Method java/io/PrintWriter.close:()V\n+        87: aload         4\n+        89: athrow\n+        90: return\n       Exception table:\n          from    to  target type\n-            11    17    24   Class java/lang/Throwable\n-            25    29    32   Class java/lang/Throwable\n+            27    31    34   Class java/lang/Throwable\n+            13    19    50   Class java/lang/Throwable\n+            13    19    55   any\n+            65    69    72   Class java/lang/Throwable\n+            50    57    55   any\n       LineNumberTable:\n         line 6: 0\n-        line 7: 11\n-        line 8: 17\n-        line 6: 24\n-        line 9: 40\n-      StackMapTable: number_of_entries = 4\n+        line 7: 13\n+        line 8: 19\n+        line 6: 50\n+        line 8: 55\n+        line 9: 90\n+      StackMapTable: number_of_entries = 8\n         frame_type = 255 /* full_frame */\n-          offset_delta = 24\n-          locals = [ class \"[Ljava/lang/String;\", class java/io/PrintWriter ]\n+          offset_delta = 34\n+          locals = [ class \"[Ljava/lang/String;\", class java/io/PrintWriter, class java/lang/Throwable ]\n+          stack = [ class java/lang/Throwable ]\n+        frame_type = 8 /* same */\n+        frame_type = 70 /* same_locals_1_stack_item */\n+          stack = [ class java/lang/Throwable ]\n+        frame_type = 68 /* same_locals_1_stack_item */\n           stack = [ class java/lang/Throwable ]\n         frame_type = 255 /* full_frame */\n-          offset_delta = 7\n-          locals = [ class \"[Ljava/lang/String;\", class java/io/PrintWriter, class java/lang/Throwable ]\n+          offset_delta = 16\n+          locals = [ class \"[Ljava/lang/String;\", class java/io/PrintWriter, class java/lang/Throwable, top, class java/lang/Throwable ]\n           stack = [ class java/lang/Throwable ]\n-        frame_type = 5 /* same */\n-        frame_type = 249 /* chop */\n-          offset_delta = 1\n+        frame_type = 10 /* same */\n+        frame_type = 3 /* same */\n+        frame_type = 255 /* full_frame */\n+          offset_delta = 2\n+          locals = [ class \"[Ljava/lang/String;\" ]\n+          stack = []\n }\n SourceFile: \"TryWithResource.java\"\n"}]}
